cooper_util.py
cooper_util-0.1.0.dist-info/WHEEL
cooper_util-0.1.0.dist-info/METADATA
cooper_util-0.1.0.dist-info/RECORD
