Metadata-Version: 2.1
Name: cooper-util
Version: 0.1.0
Summary: 
Author: Bao Hengtao
Author-email: baohengtao@users.noreply.github.com
Requires-Python: >=3.9,<4.0
Classifier: Programming Language :: Python :: 3
Classifier: Programming Language :: Python :: 3.9
Requires-Dist: loguru (>=0.5.3,<0.6.0)
Requires-Dist: rich (>=10.9.0,<11.0.0)
